CHANGES.rst
MANIFEST.in
README.rst
setup.cfg
setup.py
anybox/__init__.py
anybox.recipe.openerp.egg-info/PKG-INFO
anybox.recipe.openerp.egg-info/SOURCES.txt
anybox.recipe.openerp.egg-info/dependency_links.txt
anybox.recipe.openerp.egg-info/entry_points.txt
anybox.recipe.openerp.egg-info/namespace_packages.txt
anybox.recipe.openerp.egg-info/not-zip-safe
anybox.recipe.openerp.egg-info/requires.txt
anybox.recipe.openerp.egg-info/top_level.txt
anybox/recipe/__init__.py
anybox/recipe/openerp/__init__.py
anybox/recipe/openerp/base.py
anybox/recipe/openerp/devtools.py
anybox/recipe/openerp/gtkclient.py
anybox/recipe/openerp/openerp-cron-worker
anybox/recipe/openerp/server.py
anybox/recipe/openerp/testing.py
anybox/recipe/openerp/upgrade.py.tmpl
anybox/recipe/openerp/utils.py
anybox/recipe/openerp/webclient.py
anybox/recipe/openerp/runtime/__init__.py
anybox/recipe/openerp/runtime/patch_odoo.py
anybox/recipe/openerp/runtime/patch_openerp_v5.py
anybox/recipe/openerp/runtime/session.py
anybox/recipe/openerp/runtime/start_openerp.py
anybox/recipe/openerp/runtime/test_openerp.py
anybox/recipe/openerp/runtime/upgrade.py
anybox/recipe/openerp/runtime/backports/__init__.py
anybox/recipe/openerp/runtime/backports/cli/__init__.py
anybox/recipe/openerp/runtime/backports/cli/server.py
anybox/recipe/openerp/runtime/tests/__init__.py
anybox/recipe/openerp/runtime/tests/test_import_registry.py
anybox/recipe/openerp/tests/__init__.py
anybox/recipe/openerp/tests/test_base.py
anybox/recipe/openerp/tests/test_extract.py
anybox/recipe/openerp/tests/test_freeze.py
anybox/recipe/openerp/tests/test_server.py
anybox/recipe/openerp/tests/test_utils.py
anybox/recipe/openerp/vcs/__init__.py
anybox/recipe/openerp/vcs/base.py
anybox/recipe/openerp/vcs/bzr.py
anybox/recipe/openerp/vcs/git.py
anybox/recipe/openerp/vcs/hg.py
anybox/recipe/openerp/vcs/svn.py
anybox/recipe/openerp/vcs/testing.py
anybox/recipe/openerp/vcs/tests/__init__.py
anybox/recipe/openerp/vcs/tests/test_base.py
anybox/recipe/openerp/vcs/tests/test_bzr.py
anybox/recipe/openerp/vcs/tests/test_git.py
anybox/recipe/openerp/vcs/tests/test_hg.py
anybox/recipe/openerp/vcs/tests/test_svn.py
buildbot/base_recipe.cfg
buildbot/bootstrap.py
buildbot/recipe-50.cfg
buildbot/recipe-60-custom.cfg
buildbot/recipe-60.cfg
buildbot/recipe-61-custom.cfg
buildbot/recipe-61.cfg
buildbot/recipe-7.0.cfg
