Metadata-Version: 1.1
Name: anybox.recipe.openerp
Version: 1.9.1
Summary: A buildout recipe to install and configure OpenERP
Home-page: https://launchpad.net/anybox.recipe.openerp
Author: Anybox
Author-email: contact@anybox.fr
License: AGPLv3+
Platform: UNKNOWN
Classifier: Development Status :: 5 - Production/Stable
Classifier: Framework :: Buildout :: Recipe
Classifier: Intended Audience :: Developers
Classifier: Intended Audience :: System Administrators
Classifier: License :: OSI Approved :: GNU Affero General Public License v3 or later (AGPLv3+)
Classifier: Topic :: Software Development :: Build Tools
Classifier: Topic :: Software Development :: Libraries :: Python Modules
